{
  "name": "BuffAdventures_heartOfTheWood_medium",
  "buffs": {
    "CS_wildlife": [5],
    "CS_hearttree": [1],
    "CS_woodhealing": [10],
    "CS_Fertilizer": [1]
  },
  "steps": [
    {
      "name": "StartAdventure"
    },
    {
      "name": "VisitAdventure"
    },
    {
      "name": "CollectPickups"
    },
    {
      "name": "ReturnHome"
    },
    {
      "name": "ProduceItem",
      "data": "CS_wildlife"
    },
    {
      "name": "VisitAdventure"
    },
    {
      "name": "ApplyBuff",
      "data": "CS_wildlife"
    },
    {
      "name": "CollectPickups"
    },
    {
      "name": "ReturnHome"
    },
    {
      "name": "ProduceItem",
      "data": "CS_hearttree"
    },
    {
      "name": "VisitAdventure"
    },
    {
      "name": "ApplyBuff",
      "data": "CS_hearttree"
    },
    {
      "name": "CollectPickups"
    },
    {
      "name": "ReturnHome"
    },
    {
      "name": "ProduceItem",
      "data": "CS_woodhealing"
    },
    {
      "name": "VisitAdventure"
    },
    {
      "name": "ApplyBuff",
      "data": "CS_woodhealing"
    },
    {
      "name": "CollectPickups"
    },
    {
      "name": "ReturnHome"
    },
    {
      "name": "ProduceItem",
      "data": "CS_Fertilizer"
    },
    {
      "name": "VisitAdventure"
    },
    {
      "name": "ApplyBuff",
      "data": "CS_Fertilizer"
    }
  ]
}